{
  "project_info": {
    "project_number": "772251765553",
    "project_id": "diplomatiki-1",
    "storage_bucket": "diplomatiki-1.appspot.com"
  },
  "client": [
    {
      "client_info": {
        "mobilesdk_app_id": "1:772251765553:android:5bcd308aed8d083eafbe10",
        "android_client_info": {
          "package_name": "gio.maroon.gio_app"
        }
      },
      "oauth_client": [
        {
          "client_id": "772251765553-eu7j9bvula63k39ct7108lo2uq8usq5a.apps.googleusercontent.com",
          "client_type": 3
        }
      ],
      "api_key": [
        {
          "current_key": "AIzaSyCss5qQouw5jh3jvzRooDks5Kad3HEqcVk"
        }
      ],
      "services": {
        "appinvite_service": {
          "other_platform_oauth_client": [
            {
              "client_id": "772251765553-eu7j9bvula63k39ct7108lo2uq8usq5a.apps.googleusercontent.com",
              "client_type": 3
            }
          ]
        }
      }
    }
  ],
  "configuration_version": "1"
}